hyperta/__init__.py
hyperta/api/__init__.py
hyperta/api/routes_backtesting.py
hyperta/api/routes_data.py
hyperta/api/routes_functions.py
hyperta/api/routes_ml.py
hyperta/api/routes_strategies.py
hyperta/api/routes_utils.py
hyperta/backtesting/__init__.py
hyperta/backtesting/signalQuality.py
hyperta/data/__init__.py
hyperta/data/fetch_yfinance.py
hyperta/db/market_db.py
hyperta/functions/__init__.py
hyperta/functions/indicators/__init__.py
hyperta/functions/indicators/momentum_indicators.py
hyperta/functions/indicators/threshold_functions.py
hyperta/functions/indicators/trend_indicators.py
hyperta/functions/indicators/universal_indicator_dispatcher.py
hyperta/functions/indicators/universal_threshold_dispatcher.py
hyperta/functions/indicators/volatility_indicators.py
hyperta/functions/indicators/volume_indicators.py
hyperta/functions/metrics/universal_metrics_dispatcher.py
hyperta/functions/plots/__init__.py
hyperta/functions/plots/plot_indicators.py
hyperta/functions/plots/plot_signals.py
hyperta/functions/plots/plot_weekends.py
hyperta/functions/structures/__init__.py
hyperta/functions/structures/market_structure/__init__.py
hyperta/functions/structures/market_structure/breakouts.py
hyperta/functions/structures/market_structure/candlestick_formations.py
hyperta/functions/structures/market_structure/chart_patterns.py
hyperta/functions/structures/market_structure/divergences.py
hyperta/functions/structures/market_structure/fibonacci.py
hyperta/functions/structures/market_structure/gaps.py
hyperta/functions/structures/market_structure/hh_hl_lh_ll.py
hyperta/functions/structures/market_structure/sr_levels.py
hyperta/functions/structures/market_structure/swing_points.py
hyperta/functions/structures/market_structure/trendlines.py
hyperta/functions/structures/market_structure/volume_profile.py
hyperta/functions/structures/orderflow/__init__.py
hyperta/functions/structures/orderflow/footprint.py
hyperta/functions/structures/orderflow/liquidity_sweeps.py
hyper_ta-0.0.2.dist-info/METADATA
hyper_ta-0.0.2.dist-info/WHEEL
hyper_ta-0.0.2.dist-info/top_level.txt
hyper_ta-0.0.2.dist-info/RECORD
