Metadata-Version: 2.4
Name: Hyper-TA
Version: 0.0.2
Summary: Automatic technical analysis framework.
Author-email: Panagiotis Mokos <12345678+MwkosP@users.noreply.github.com>
Project-URL: Homepage, https://github.com/MwkosP
Requires-Dist: requests
